[{"sciName":"Zizina otis","comName":"Lesser Grass Blue","noOfObs":"3","locations":["National Museum of Singapore, SG","National Museum of Singapore, Singapore, Singapore, SG","122 Middle Rd, Singapore 188973",""],"url":"https://www.inaturalist.org/observations?iconic_taxa=Insecta&nelat=1.3046128097445413&nelng=103.85494125618739&place_id=any&subview=map&swlat=1.2961637496835838&swlng=103.8490226572699&view=&taxon_id=125537&page="},{"sciName":"Apis cerana","comName":"Asian Honey Bee","noOfObs":"3","locations":["National Museum of Singapore, SG","1 McNally Street, Singapore, Singapore, SG","SMU Li Ka Shing Lib, Singapore, Singapore, SG",""],"url":"https://www.inaturalist.org/observations?iconic_taxa=Insecta&nelat=1.3046128097445413&nelng=103.85494125618739&place_id=any&subview=map&swlat=1.2961637496835838&swlng=103.8490226572699&view=&taxon_id=338194&page="},{"sciName":"Papilio demoleus","comName":"Lime Swallowtail","noOfObs":"2","locations":["1.3001012547,103.8507736951","Middle Road, Singapore, Singapore, SG",""],"url":"https://www.inaturalist.org/observations?iconic_taxa=Insecta&nelat=1.3046128097445413&nelng=103.85494125618739&place_id=any&subview=map&swlat=1.2961637496835838&swlng=103.8490226572699&view=&taxon_id=51583&page="},{"sciName":"","comName":"Can't find name","noOfObs":"2","locations":["Waterloo Street, Singapore, Singapore, SG","Queen Street, Singapore, Singapore, SG",""],"url":"https://www.inaturalist.org/observations?iconic_taxa=Insecta&nelat=1.3046128097445413&nelng=103.85494125618739&place_id=any&subview=map&swlat=1.2961637496835838&swlng=103.8490226572699&view=&taxon_id=82040&page="},{"sciName":"Acraea terpsicore","comName":"Tawny Coster","noOfObs":"2","locations":["National Museum of Singapore, Singapore, Singapore, SG","Bras Basah, Singapore",""],"url":"https://www.inaturalist.org/observations?iconic_taxa=Insecta&nelat=1.3046128097445413&nelng=103.85494125618739&place_id=any&subview=map&swlat=1.2961637496835838&swlng=103.8490226572699&view=&taxon_id=180386&page="},{"sciName":"Trilocha varians","comName":"Greenish Silk-Moth","noOfObs":"2","locations":["Bras Basah, Singapore","108 Middle Road, Singapore, Singapore, SG",""],"url":"https://www.inaturalist.org/observations?iconic_taxa=Insecta&nelat=1.3046128097445413&nelng=103.85494125618739&place_id=any&subview=map&swlat=1.2961637496835838&swlng=103.8490226572699&view=&taxon_id=193959&page="},{"sciName":"Amata huebneri","comName":"Hübner's Wasp Moth","noOfObs":"2","locations":["Bras Basah, Singapore","Niven Road, Newton, Singapore, SG",""],"url":"https://www.inaturalist.org/observations?iconic_taxa=Insecta&nelat=1.3046128097445413&nelng=103.85494125618739&place_id=any&subview=map&swlat=1.2961637496835838&swlng=103.8490226572699&view=&taxon_id=354050&page="},{"sciName":"","comName":"Can't find name","noOfObs":"2","locations":["Prinsep Street, Singapore, Singapore, SG","48 Bencoolen Street, Singapore, Singapore, SG",""],"url":"https://www.inaturalist.org/observations?iconic_taxa=Insecta&nelat=1.3046128097445413&nelng=103.85494125618739&place_id=any&subview=map&swlat=1.2961637496835838&swlng=103.8490226572699&view=&taxon_id=369810&page="},{"sciName":"","comName":"Can't find name","noOfObs":"2","locations":["Waterloo Street, Singapore, Singapore, SG","51 Bras Basah Road, Singapore, Singapore, SG",""],"url":"https://www.inaturalist.org/observations?iconic_taxa=Insecta&nelat=1.3046128097445413&nelng=103.85494125618739&place_id=any&subview=map&swlat=1.2961637496835838&swlng=103.8490226572699&view=&taxon_id=474489&page="},{"sciName":"","comName":"Can't find name","noOfObs":"2","locations":["Victoria Street, Singapore, Singapore, SG","73 Bras Basah Road, Singapore, Singapore, SG",""],"url":"https://www.inaturalist.org/observations?iconic_taxa=Insecta&nelat=1.3046128097445413&nelng=103.85494125618739&place_id=any&subview=map&swlat=1.2961637496835838&swlng=103.8490226572699&view=&taxon_id=516006&page="},{"sciName":"Noctuidae","comName":"Family Cutworm Moths and Allies","noOfObs":"1","locations":["Middle Road, Singapore, Singapore, SG",""],"url":"https://www.inaturalist.org/observations?iconic_taxa=Insecta&nelat=1.3046128097445413&nelng=103.85494125618739&place_id=any&subview=map&swlat=1.2961637496835838&swlng=103.8490226572699&view=&taxon_id=48670&page="},{"sciName":"Daphnis nerii","comName":"Oleander Hawkmoth","noOfObs":"1","locations":["Albert Street, Singapore, Singapore, SG",""],"url":"https://www.inaturalist.org/observations?iconic_taxa=Insecta&nelat=1.3046128097445413&nelng=103.85494125618739&place_id=any&subview=map&swlat=1.2961637496835838&swlng=103.8490226572699&view=&taxon_id=51996&page="},{"sciName":"Sameodes cancellalis","comName":"Banded Pearl","noOfObs":"1","locations":["26 Waterloo Street, Singapore, Singapore, SG",""],"url":"https://www.inaturalist.org/observations?iconic_taxa=Insecta&nelat=1.3046128097445413&nelng=103.85494125618739&place_id=any&subview=map&swlat=1.2961637496835838&swlng=103.8490226572699&view=&taxon_id=52038&page="},{"sciName":"Tingidae","comName":"Family Lace Bugs","noOfObs":"1","locations":["Waterloo Street, Singapore, Singapore, SG",""],"url":"https://www.inaturalist.org/observations?iconic_taxa=Insecta&nelat=1.3046128097445413&nelng=103.85494125618739&place_id=any&subview=map&swlat=1.2961637496835838&swlng=103.8490226572699&view=&taxon_id=53506&page="},{"sciName":"Phoridae","comName":"Family Humpbacked Flies","noOfObs":"1","locations":["McNally Street, Singapore, Singapore, SG",""],"url":"https://www.inaturalist.org/observations?iconic_taxa=Insecta&nelat=1.3046128097445413&nelng=103.85494125618739&place_id=any&subview=map&swlat=1.2961637496835838&swlng=103.8490226572699&view=&taxon_id=55351&page="},{"sciName":"Gracillariidae","comName":"Family Leaf Blotch Miner Moths","noOfObs":"1","locations":["Rochor Canal Road, Singapore, Singapore, SG",""],"url":"https://www.inaturalist.org/observations?iconic_taxa=Insecta&nelat=1.3046128097445413&nelng=103.85494125618739&place_id=any&subview=map&swlat=1.2961637496835838&swlng=103.8490226572699&view=&taxon_id=61353&page="},{"sciName":"Psychidae","comName":"Family Bagworm Moths","noOfObs":"1","locations":["Bugis+, Singapore, Singapore, SG",""],"url":"https://www.inaturalist.org/observations?iconic_taxa=Insecta&nelat=1.3046128097445413&nelng=103.85494125618739&place_id=any&subview=map&swlat=1.2961637496835838&swlng=103.8490226572699&view=&taxon_id=61415&page="},{"sciName":"Sitophilus","comName":"Genus Grain Weevils","noOfObs":"1","locations":["Singapore",""],"url":"https://www.inaturalist.org/observations?iconic_taxa=Insecta&nelat=1.3046128097445413&nelng=103.85494125618739&place_id=any&subview=map&swlat=1.2961637496835838&swlng=103.8490226572699&view=&taxon_id=63711&page="},{"sciName":"Drosophilidae","comName":"Family Vinegar and Fruit Flies","noOfObs":"1","locations":["McNally Street, Singapore, Singapore, SG",""],"url":"https://www.inaturalist.org/observations?iconic_taxa=Insecta&nelat=1.3046128097445413&nelng=103.85494125618739&place_id=any&subview=map&swlat=1.2961637496835838&swlng=103.8490226572699&view=&taxon_id=67742&page="},{"sciName":"","comName":"Can't find name","noOfObs":"1","locations":["SMU Sch of Econ & Social Sc, Singapore, Singapore, SG",""],"url":"https://www.inaturalist.org/observations?iconic_taxa=Insecta&nelat=1.3046128097445413&nelng=103.85494125618739&place_id=any&subview=map&swlat=1.2961637496835838&swlng=103.8490226572699&view=&taxon_id=69778&page="},{"sciName":"Nannophya pygmaea","comName":"Scarlet Pygmy","noOfObs":"1","locations":["190 Middle Road, Singapore, Singapore, SG",""],"url":"https://www.inaturalist.org/observations?iconic_taxa=Insecta&nelat=1.3046128097445413&nelng=103.85494125618739&place_id=any&subview=map&swlat=1.2961637496835838&swlng=103.8490226572699&view=&taxon_id=106513&page="},{"sciName":"Trithemis aurora","comName":"Crimson Dropwing","noOfObs":"1","locations":["Bras Basah Complex, Singapore, Singapore, SG",""],"url":"https://www.inaturalist.org/observations?iconic_taxa=Insecta&nelat=1.3046128097445413&nelng=103.85494125618739&place_id=any&subview=map&swlat=1.2961637496835838&swlng=103.8490226572699&view=&taxon_id=114466&page="},{"sciName":"Acrida","comName":"Genus Slantface Grasshoppers","noOfObs":"1","locations":["142 Prinsep Street, Singapore, Singapore, SG",""],"url":"https://www.inaturalist.org/observations?iconic_taxa=Insecta&nelat=1.3046128097445413&nelng=103.85494125618739&place_id=any&subview=map&swlat=1.2961637496835838&swlng=103.8490226572699&view=&taxon_id=119686&page="},{"sciName":"","comName":"Can't find name","noOfObs":"1","locations":["McNally Street, Singapore, Singapore, SG",""],"url":"https://www.inaturalist.org/observations?iconic_taxa=Insecta&nelat=1.3046128097445413&nelng=103.85494125618739&place_id=any&subview=map&swlat=1.2961637496835838&swlng=103.8490226572699&view=&taxon_id=120366&page="},{"sciName":"Phycitinae","comName":"Subfamily Knot-horn Moths","noOfObs":"1","locations":["Prinsep Street, Singapore, Singapore, SG",""],"url":"https://www.inaturalist.org/observations?iconic_taxa=Insecta&nelat=1.3046128097445413&nelng=103.85494125618739&place_id=any&subview=map&swlat=1.2961637496835838&swlng=103.8490226572699&view=&taxon_id=122925&page="},{"sciName":"","comName":"Can't find name","noOfObs":"1","locations":["Albert Street, Singapore, Singapore, SG",""],"url":"https://www.inaturalist.org/observations?iconic_taxa=Insecta&nelat=1.3046128097445413&nelng=103.85494125618739&place_id=any&subview=map&swlat=1.2961637496835838&swlng=103.8490226572699&view=&taxon_id=124068&page="},{"sciName":"Pygospila tyres","comName":"Chequered Snout","noOfObs":"1","locations":["Bencoolen Street, Singapore, Singapore, SG",""],"url":"https://www.inaturalist.org/observations?iconic_taxa=Insecta&nelat=1.3046128097445413&nelng=103.85494125618739&place_id=any&subview=map&swlat=1.2961637496835838&swlng=103.8490226572699&view=&taxon_id=124872&page="},{"sciName":"Ochthera","comName":"Genus Mantid Shoreflies","noOfObs":"1","locations":["Annamalai Chitty Lane, Singapore, Singapore, SG",""],"url":"https://www.inaturalist.org/observations?iconic_taxa=Insecta&nelat=1.3046128097445413&nelng=103.85494125618739&place_id=any&subview=map&swlat=1.2961637496835838&swlng=103.8490226572699&view=&taxon_id=132236&page="},{"sciName":"Limenitidinae","comName":"Subfamily Admirals and Allies","noOfObs":"1","locations":["155 Waterloo Street, Singapore, Singapore, SG",""],"url":"https://www.inaturalist.org/observations?iconic_taxa=Insecta&nelat=1.3046128097445413&nelng=103.85494125618739&place_id=any&subview=map&swlat=1.2961637496835838&swlng=103.8490226572699&view=&taxon_id=134171&page="},{"sciName":"Pseudozizeeria maha","comName":"Pale Grass Blue","noOfObs":"1","locations":["Waterloo Street, Singapore, Singapore, SG",""],"url":"https://www.inaturalist.org/observations?iconic_taxa=Insecta&nelat=1.3046128097445413&nelng=103.85494125618739&place_id=any&subview=map&swlat=1.2961637496835838&swlng=103.8490226572699&view=&taxon_id=145642&page="},{"sciName":"Cantao ocellatus","comName":"Ocellated Shield Bug","noOfObs":"1","locations":["144 Prinsep Street, Singapore, Singapore, SG",""],"url":"https://www.inaturalist.org/observations?iconic_taxa=Insecta&nelat=1.3046128097445413&nelng=103.85494125618739&place_id=any&subview=map&swlat=1.2961637496835838&swlng=103.8490226572699&view=&taxon_id=145656&page="},{"sciName":"Suastus gremius","comName":"Indian Palm Bob","noOfObs":"1","locations":["210 Middle Road, Singapore, Singapore, SG",""],"url":"https://www.inaturalist.org/observations?iconic_taxa=Insecta&nelat=1.3046128097445413&nelng=103.85494125618739&place_id=any&subview=map&swlat=1.2961637496835838&swlng=103.8490226572699&view=&taxon_id=154731&page="},{"sciName":"","comName":"Can't find name","noOfObs":"1","locations":["Prinsep Street, Singapore, Singapore, SG",""],"url":"https://www.inaturalist.org/observations?iconic_taxa=Insecta&nelat=1.3046128097445413&nelng=103.85494125618739&place_id=any&subview=map&swlat=1.2961637496835838&swlng=103.8490226572699&view=&taxon_id=180701&page="},{"sciName":"Chalciope mygdon","comName":"Triangular-striped Moth","noOfObs":"1","locations":["111 Middle Road, Singapore, Singapore, SG",""],"url":"https://www.inaturalist.org/observations?iconic_taxa=Insecta&nelat=1.3046128097445413&nelng=103.85494125618739&place_id=any&subview=map&swlat=1.2961637496835838&swlng=103.8490226572699&view=&taxon_id=203112&page="},{"sciName":"","comName":"Can't find name","noOfObs":"1","locations":["Bencoolen Street, Singapore, Singapore, SG",""],"url":"https://www.inaturalist.org/observations?iconic_taxa=Insecta&nelat=1.3046128097445413&nelng=103.85494125618739&place_id=any&subview=map&swlat=1.2961637496835838&swlng=103.8490226572699&view=&taxon_id=203868&page="},{"sciName":"","comName":"Can't find name","noOfObs":"1","locations":["Waterloo Street, Singapore, Singapore, SG",""],"url":"https://www.inaturalist.org/observations?iconic_taxa=Insecta&nelat=1.3046128097445413&nelng=103.85494125618739&place_id=any&subview=map&swlat=1.2961637496835838&swlng=103.8490226572699&view=&taxon_id=250262&page="},{"sciName":"","comName":"Can't find name","noOfObs":"1","locations":["McNally Street, Singapore, Singapore, SG",""],"url":"https://www.inaturalist.org/observations?iconic_taxa=Insecta&nelat=1.3046128097445413&nelng=103.85494125618739&place_id=any&subview=map&swlat=1.2961637496835838&swlng=103.8490226572699&view=&taxon_id=310356&page="},{"sciName":"Doleschallia bisaltide","comName":"Autumn Leaf","noOfObs":"1","locations":["Singapore",""],"url":"https://www.inaturalist.org/observations?iconic_taxa=Insecta&nelat=1.3046128097445413&nelng=103.85494125618739&place_id=any&subview=map&swlat=1.2961637496835838&swlng=103.8490226572699&view=&taxon_id=311421&page="},{"sciName":"Papilio clytia","comName":"Common Mime Swallowtail","noOfObs":"1","locations":["National Museum of Singapore, Singapore, Singapore, SG",""],"url":"https://www.inaturalist.org/observations?iconic_taxa=Insecta&nelat=1.3046128097445413&nelng=103.85494125618739&place_id=any&subview=map&swlat=1.2961637496835838&swlng=103.8490226572699&view=&taxon_id=319069&page="},{"sciName":"Pelopidas agna","comName":"Little Branded Swift","noOfObs":"1","locations":["144 Prinsep Street, Singapore, Singapore, SG",""],"url":"https://www.inaturalist.org/observations?iconic_taxa=Insecta&nelat=1.3046128097445413&nelng=103.85494125618739&place_id=any&subview=map&swlat=1.2961637496835838&swlng=103.8490226572699&view=&taxon_id=322529&page="},{"sciName":"Hyarotis adrastus","comName":"Tree Flitter","noOfObs":"1","locations":["1.2974682405,103.8500241987",""],"url":"https://www.inaturalist.org/observations?iconic_taxa=Insecta&nelat=1.3046128097445413&nelng=103.85494125618739&place_id=any&subview=map&swlat=1.2961637496835838&swlng=103.8490226572699&view=&taxon_id=324446&page="},{"sciName":"Borbo cinnara","comName":"Formosan Swift","noOfObs":"1","locations":["Bencoolen Street, Singapore, Singapore, SG",""],"url":"https://www.inaturalist.org/observations?iconic_taxa=Insecta&nelat=1.3046128097445413&nelng=103.85494125618739&place_id=any&subview=map&swlat=1.2961637496835838&swlng=103.8490226572699&view=&taxon_id=326007&page="},{"sciName":"","comName":"Can't find name","noOfObs":"1","locations":["Middle Road",""],"url":"https://www.inaturalist.org/observations?iconic_taxa=Insecta&nelat=1.3046128097445413&nelng=103.85494125618739&place_id=any&subview=map&swlat=1.2961637496835838&swlng=103.8490226572699&view=&taxon_id=330040&page="},{"sciName":"Coccinella transversalis","comName":"Small Transverse Ladybird Beetle","noOfObs":"1","locations":["1 McNally Street, Singapore, Singapore, SG",""],"url":"https://www.inaturalist.org/observations?iconic_taxa=Insecta&nelat=1.3046128097445413&nelng=103.85494125618739&place_id=any&subview=map&swlat=1.2961637496835838&swlng=103.8490226572699&view=&taxon_id=349064&page="},{"sciName":"","comName":"Can't find name","noOfObs":"1","locations":["14–15 Queen Street, Singapore, Singapore, SG",""],"url":"https://www.inaturalist.org/observations?iconic_taxa=Insecta&nelat=1.3046128097445413&nelng=103.85494125618739&place_id=any&subview=map&swlat=1.2961637496835838&swlng=103.8490226572699&view=&taxon_id=356051&page="},{"sciName":"Prosotas dubiosa","comName":"Tailless Lineblue","noOfObs":"1","locations":["SMU Li Ka Shing Lib, Singapore, Singapore, SG",""],"url":"https://www.inaturalist.org/observations?iconic_taxa=Insecta&nelat=1.3046128097445413&nelng=103.85494125618739&place_id=any&subview=map&swlat=1.2961637496835838&swlng=103.8490226572699&view=&taxon_id=356143&page="},{"sciName":"","comName":"Can't find name","noOfObs":"1","locations":["Waterloo Street, Singapore, Singapore, SG",""],"url":"https://www.inaturalist.org/observations?iconic_taxa=Insecta&nelat=1.3046128097445413&nelng=103.85494125618739&place_id=any&subview=map&swlat=1.2961637496835838&swlng=103.8490226572699&view=&taxon_id=363553&page="},{"sciName":"","comName":"Can't find name","noOfObs":"1","locations":["Albert Street, Singapore, Singapore, SG",""],"url":"https://www.inaturalist.org/observations?iconic_taxa=Insecta&nelat=1.3046128097445413&nelng=103.85494125618739&place_id=any&subview=map&swlat=1.2961637496835838&swlng=103.8490226572699&view=&taxon_id=479748&page="},{"sciName":"Valanga nigricornis","comName":"Javanese Grasshopper","noOfObs":"1","locations":["Waterloo Street, Singapore, Singapore, SG",""],"url":"https://www.inaturalist.org/observations?iconic_taxa=Insecta&nelat=1.3046128097445413&nelng=103.85494125618739&place_id=any&subview=map&swlat=1.2961637496835838&swlng=103.8490226572699&view=&taxon_id=493892&page="},{"sciName":"","comName":"Can't find name","noOfObs":"1","locations":["122 Middle Road, Singapore, Singapore, SG",""],"url":"https://www.inaturalist.org/observations?iconic_taxa=Insecta&nelat=1.3046128097445413&nelng=103.85494125618739&place_id=any&subview=map&swlat=1.2961637496835838&swlng=103.8490226572699&view=&taxon_id=528299&page="},{"sciName":"","comName":"Can't find name","noOfObs":"1","locations":["73–75 Bras Basah Road, Singapore, Singapore, SG",""],"url":"https://www.inaturalist.org/observations?iconic_taxa=Insecta&nelat=1.3046128097445413&nelng=103.85494125618739&place_id=any&subview=map&swlat=1.2961637496835838&swlng=103.8490226572699&view=&taxon_id=556182&page="},{"sciName":"","comName":"Can't find name","noOfObs":"1","locations":["McNally Street, Singapore, Singapore, SG",""],"url":"https://www.inaturalist.org/observations?iconic_taxa=Insecta&nelat=1.3046128097445413&nelng=103.85494125618739&place_id=any&subview=map&swlat=1.2961637496835838&swlng=103.8490226572699&view=&taxon_id=639674&page="},{"sciName":"","comName":"Can't find name","noOfObs":"1","locations":["Middle Road, Singapore, Singapore, SG",""],"url":"https://www.inaturalist.org/observations?iconic_taxa=Insecta&nelat=1.3046128097445413&nelng=103.85494125618739&place_id=any&subview=map&swlat=1.2961637496835838&swlng=103.8490226572699&view=&taxon_id=752206&page="},{"sciName":"","comName":"Can't find name","noOfObs":"1","locations":["10–11 Prinsep Link, Singapore, Singapore, SG",""],"url":"https://www.inaturalist.org/observations?iconic_taxa=Insecta&nelat=1.3046128097445413&nelng=103.85494125618739&place_id=any&subview=map&swlat=1.2961637496835838&swlng=103.8490226572699&view=&taxon_id=784829&page="},{"sciName":"","comName":"Can't find name","noOfObs":"1","locations":["1.3019752703,103.8501643084",""],"url":"https://www.inaturalist.org/observations?iconic_taxa=Insecta&nelat=1.3046128097445413&nelng=103.85494125618739&place_id=any&subview=map&swlat=1.2961637496835838&swlng=103.8490226572699&view=&taxon_id=877077&page="},{"sciName":"Marasmia poeyalis","comName":"Lesser Rice-Leafroller","noOfObs":"1","locations":["Prinsep Street, Singapore, Singapore, SG",""],"url":"https://www.inaturalist.org/observations?iconic_taxa=Insecta&nelat=1.3046128097445413&nelng=103.85494125618739&place_id=any&subview=map&swlat=1.2961637496835838&swlng=103.8490226572699&view=&taxon_id=1273862&page="}]